README.txt
setup.py
pyulogin/README.txt
pyulogin/__init__.py
pyulogin/exceptions.py
pyulogin/license.txt
pyulogin/ulogin.py
pyulogin/ulogin_manager.py
pyulogin/user.py
pyulogin.egg-info/PKG-INFO
pyulogin.egg-info/SOURCES.txt
pyulogin.egg-info/dependency_links.txt
pyulogin.egg-info/top_level.txt