Metadata-Version: 1.1
Name: pyulogin
Version: 0.0.3
Summary: Package for work with service ulogin.ru
Home-page: https://github.com/GDAproj/pyulogin
Author: Gurov Dmitri
Author-email: opengurdev@gmail.com
License: MIT
Keywords: uLogin
Platform: UNKNOWN
Classifier: Development Status :: 2 - Pre-Alpha
Classifier: Environment :: Web Environment
Classifier: License :: OSI Approved :: MIT License
